claudemyth01.sourjuice-0.0.1-py2.7-nspkg.pth
claudemyth01/sourjuice/__init__.py
claudemyth01/sourjuice/j.py
claudemyth01.sourjuice-0.0.1.dist-info/METADATA
claudemyth01.sourjuice-0.0.1.dist-info/WHEEL
claudemyth01.sourjuice-0.0.1.dist-info/namespace_packages.txt
claudemyth01.sourjuice-0.0.1.dist-info/top_level.txt
claudemyth01.sourjuice-0.0.1.dist-info/RECORD
