Metadata-Version: 2.1
Name: claudemyth01.sourjuice
Version: 0.0.1
Summary: Loving sour juice
Home-page: UNKNOWN
Author: UNKNOWN
Author-email: UNKNOWN
License: UNKNOWN
Platform: UNKNOWN
Classifier: Programming Language :: Python :: 2
Classifier: Operating System :: OS Independent
